README.md
setup.py
joker_tool/__init__.py
joker_tool/base_tool.py
joker_tool/db_client.py
joker_tool/encrypt.py
joker_tool/img_dispose.py
joker_tool/send_dingding.py
joker_tool.egg-info/PKG-INFO
joker_tool.egg-info/SOURCES.txt
joker_tool.egg-info/dependency_links.txt
joker_tool.egg-info/top_level.txt