Metadata-Version: 2.1
Name: joker-tool
Version: 0.0.4
Summary: This is a toolkit
Home-page: https://github.com/Mrzsy/Tool
Author: Joker
Author-email: joker.code@qq.com
License: UNKNOWN
Platform: UNKNOWN
Classifier: Programming Language :: Python :: 3.8
Classifier: License :: OSI Approved :: MIT License
Classifier: Operating System :: OS Independent
Requires-Python: >=3.6
